GesundheitPerTuttiSaraPi/GesundheitPerTuttiSaraPi_module.py
GesundheitPerTuttiSaraPi/__init__.py
GesundheitPerTuttiSaraPi-0.2.3.dist-info/LICENSE
GesundheitPerTuttiSaraPi-0.2.3.dist-info/METADATA
GesundheitPerTuttiSaraPi-0.2.3.dist-info/WHEEL
GesundheitPerTuttiSaraPi-0.2.3.dist-info/entry_points.txt
GesundheitPerTuttiSaraPi-0.2.3.dist-info/top_level.txt
GesundheitPerTuttiSaraPi-0.2.3.dist-info/RECORD
