Metadata-Version: 2.1
Name: GesundheitPerTuttiSaraPi
Version: 0.2.3
Summary: Gesundheit per tutti
Home-page: https://github.com/pypa/sampleproject
Author: Sara Picciau
Author-email: spicciau@unibz.it
License: UNKNOWN
Project-URL: Bug Tracker, https://github.com/pypa/sampleproject/issues
Platform: UNKNOWN
Classifier: Programming Language :: Python :: 3
Classifier: License :: OSI Approved :: MIT License
Classifier: Operating System :: OS Independent
Requires-Python: >=3.6
Requires-Dist: gTTS
Requires-Dist: Translator
Requires-Dist: easyocr
